xpath_validator
