Metadata-Version: 1.1
Name: xpath-validator
Version: 1.5.1
Summary: validate boolean expressions with XPath syntax
Home-page: https://github.com/znc-sistemas/xpath_validator/
Author: Marcelo Fonseca Tambalo
Author-email: marcelo.tambalo@nectosystems.com.br
License: MIT
Keywords: XPath
Platform: UNKNOWN
Classifier: Development Status :: 5 - Production/Stable
Classifier: License :: OSI Approved :: MIT License
Classifier: Natural Language :: English
Classifier: Operating System :: OS Independent
Classifier: Programming Language :: Python :: 2.7
Classifier: Programming Language :: Python :: 3.6
Classifier: Programming Language :: Python :: Implementation
Classifier: Topic :: Software Development :: Libraries
